qarnot/__init__.py
qarnot/_filter.py
qarnot/_retry.py
qarnot/_util.py
qarnot/_version.py
qarnot/advanced_bucket.py
qarnot/bucket.py
qarnot/carbon_facts.py
qarnot/computing_quotas.py
qarnot/connection.py
qarnot/error.py
qarnot/exceptions.py
qarnot/forced_constant.py
qarnot/forced_network_rule.py
qarnot/hardware_constraint.py
qarnot/helper.py
qarnot/job.py
qarnot/paginate.py
qarnot/pool.py
qarnot/privileges.py
qarnot/retry_settings.py
qarnot/scheduling_type.py
qarnot/secrets.py
qarnot/status.py
qarnot/storage.py
qarnot/task.py
qarnot-2.18.0.dist-info/licenses/LICENSE
qarnot-2.18.0.dist-info/METADATA
qarnot-2.18.0.dist-info/WHEEL
qarnot-2.18.0.dist-info/top_level.txt
qarnot-2.18.0.dist-info/RECORD
