Metadata-Version: 2.4
Name: qarnot
Version: 2.18.0
Summary: Qarnot Computing SDK
Home-page: https://computing.qarnot.com
Author: Qarnot computing
Author-email: support@qarnot-computing.com
License: apache
Classifier: Development Status :: 5 - Production/Stable
Classifier: Programming Language :: Python :: 3.6
Classifier: Programming Language :: Python :: 3.7
Classifier: Programming Language :: Python :: 3.8
Classifier: Programming Language :: Python :: 3.9
Classifier: Intended Audience :: Developers
Classifier: Intended Audience :: Information Technology
Classifier: License :: OSI Approved :: Apache Software License
Requires-Python: >=3.6
License-File: LICENSE
Requires-Dist: requests
Requires-Dist: boto3>=1.36
Requires-Dist: wheel
Requires-Dist: deprecation
Requires-Dist: simplejson
Dynamic: author
Dynamic: author-email
Dynamic: classifier
Dynamic: description
Dynamic: home-page
Dynamic: license
Dynamic: license-file
Dynamic: requires-dist
Dynamic: requires-python
Dynamic: summary
